propzen/__init__.py
propzen/common/__init__.py
propzen/common/config.py
propzen/common/adapters/__init__.py
propzen/common/adapters/rabbitmq/__init__.py
propzen/common/adapters/rabbitmq/connection.py
propzen/common/adapters/rabbitmq/externalconsumer.py
propzen/common/adapters/rabbitmq/externalpublisher.py
propzen/common/adapters/sqlalchemy/__init__.py
propzen/common/adapters/sqlalchemy/database.py
propzen/common/adapters/sqlalchemy/entity_extensions.py
propzen/common/domain/__init__.py
propzen/common/domain/entity.py
propzen/common/domain/event.py
propzen/common/domain/exceptions.py
propzen/common/domain/repository.py
propzen/common/external_events/__init__.py
propzen/common/external_events/accounts.py
propzen/common/external_events/finance.py
propzen/common/external_events/fs.py
propzen/common/external_events/realestate.py
propzen/common/external_events/utility.py
propzen/common/service_layer/__init__.py
propzen/common/service_layer/command.py
propzen/common/service_layer/externalbus.py
propzen/common/service_layer/uow.py
propzen_common-0.25.0.dist-info/LICENSE.txt
propzen_common-0.25.0.dist-info/METADATA
propzen_common-0.25.0.dist-info/WHEEL
propzen_common-0.25.0.dist-info/top_level.txt
propzen_common-0.25.0.dist-info/zip-safe
propzen_common-0.25.0.dist-info/RECORD
