Metadata-Version: 2.1
Name: propzen-common
Version: 0.25.0
Summary: Common package for PropZen
Home-page: http://pypi.python.org/pypi/propzen-common
Author: Mikhail Christian Peralta
Author-email: mikhail.peralta@gmail.com
Maintainer: Mikhail Christian Peralta
Maintainer-email: mikhail.peralta@gmail.com
License: MIT
Requires-Python: >=3.9
License-File: LICENSE.txt
Requires-Dist: pydantic
Requires-Dist: python-dotenv
Requires-Dist: sqlalchemy
Requires-Dist: dataclasses-json
Requires-Dist: pika
Requires-Dist: tenacity
